{
    "DNDConfig": null,
    "__parentReadjusting__": false,
    "_height_": {
        "type": "string",
        "value": "30dp"
    },
    "_margin_": [
        0,
        0,
        0,
        0
    ],
    "_orientation_": 6,
    "_padding_": [
        0,
        0,
        0,
        0
    ],
    "_percent_": true,
    "_right_": {
        "type": "string",
        "value": "20dp"
    },
    "_skin_": "s90d1dcb77b84f85bf5207fa207c38c6",
    "_width_": {
        "type": "string",
        "value": "50dp"
    },
    "allboxes": [],
    "autogrowmode": 0,
    "canUpdateUI": true,
    "centery": {
        "type": "string",
        "value": "50%"
    },
    "children": [
        "flxSwitchToggleEmail"
    ],
    "clipbounds": true,
    "containerweight": 100,
    "enablescrolling": true,
    "id": "flxSwitchEmail",
    "info": null,
    "iscustomlayout": false,
    "isvisible": false,
    "kuid": "a3324b386e104e568c719fd195c2ebf6",
    "layouttype": 2,
    "name": "kony.ui.FlexContainer",
    "parent": "flxEmail",
    "pf": "frmAccountMinimumBalance",
    "retaincontentalignment": false,
    "retainflexpositionproperties": false,
    "snapgridsize": 10,
    "snaptogrid": true,
    "wType": "FlexContainer",
    "widgetalignment": 1,
    "zindex": 1
}