{
    "@class": "com.kony.gen.viz.model.component.KVizButton",
    "DNDConfig": null,
    "__parentReadjusting__": false,
    "_bottom_": {
        "type": "string",
        "value": "20dp"
    },
    "_height_": {
        "type": "string",
        "value": "40dp"
    },
    "_margin_": [
        6,
        6,
        6,
        6
    ],
    "_padding_": [
        0,
        0,
        0,
        0
    ],
    "_skin_": "s5c56a9302c04f598b5208bf315c4e14",
    "_text_": "",
    "_width_": {
        "type": "string",
        "value": "87%"
    },
    "accessibilityconfig": {
        "a11yHint": "Tap Set as Default to make this the default choice",
        "a11yLabel": "Set as Default"
    },
    "canUpdateUI": true,
    "centerx": {
        "type": "string",
        "value": "50%"
    },
    "containerweight": 100,
    "contentalignment": 5,
    "disabledSkins": {},
    "displaytext": true,
    "focusskin": "sd85a0f475ff4b3b9f0a5e4b82f68213",
    "id": "btnEnable",
    "ide_onClick": "AS_Button_d057008ae99e444f869efc1a4e927b40",
    "info": null,
    "isvisible": true,
    "kuid": "d4189ba94ef449ab8c177f484cc85688",
    "name": "kony.ui.Button",
    "parent": "flxRenterNewPin",
    "pf": "frmDevRegPin",
    "texti18n": "kony.mb.devReg.enableNSetDefault",
    "wType": "Button",
    "zindex": 1
}