{
    "@class": "com.kony.gen.viz.model.component.KVizUserWidget",
    "DNDConfig": null,
    "__parentReadjusting__": false,
    "_children_": [],
    "_height_": {
        "type": "string",
        "value": "100%"
    },
    "_left_": {
        "type": "string",
        "value": "0dp"
    },
    "_margin_": [
        0,
        0,
        0,
        0
    ],
    "_orientation_": 1,
    "_padding_": [
        0,
        0,
        0,
        0
    ],
    "_percent_": true,
    "_render_": true,
    "_skin_": "s966eaf1ea1441148b4828270a782f8b",
    "_top_": {
        "type": "string",
        "value": "0dp"
    },
    "_width_": {
        "type": "string",
        "value": "100%"
    },
    "areflexpropsreferenced": false,
    "canUpdateUI": true,
    "clipbounds": false,
    "containerweight": 0,
    "dataDiffs": {
        "btnLeft": {
            "__events__": {},
            "__info__": {
                "kuid": "dd06b12bf20341758d08c82fcf768a4f",
                "srcKUID": "a92fc4f8fe924a5a95a2b7f3de772c04",
                "wType": "Button"
            }
        },
        "btnRight": {
            "__events__": {},
            "__info__": {
                "kuid": "h780392536da42499fd661312f3c3feb",
                "srcKUID": "a4ee84ad1d214582898217af1d05a7d5",
                "wType": "Button"
            },
            "isVisible": true,
            "i18n_text": "kony.mb.common.Cancel",
            "text": "Cancel"
        },
        "customHeader": {
            "__events__": {},
            "__info__": {
                "isRoot": true,
                "kuid": "d856b694a32049c8b710d5f4ec026828",
                "srcKUID": "cf270a797f14497bb1bba45b251f1a06",
                "wType": "FlexContainer"
            }
        },
        "flxBack": {
            "__events__": {},
            "__info__": {
                "kuid": "f0f9bc28bbe446819e3a5d0b3e29b86d",
                "srcKUID": "dd5ab076f18a49149f542c0d2b517ac2",
                "wType": "FlexContainer"
            }
        },
        "flxHeader": {
            "__events__": {},
            "__info__": {
                "kuid": "d31a9f9cff9d478bbbc41ed589c6250d",
                "srcKUID": "d9ee03385e1f41a79b8e123b6dda48c5",
                "wType": "FlexContainer"
            }
        },
        "flxHeaderShadow": {
            "__events__": {},
            "__info__": {
                "kuid": "d1c326b85f8c4f3c994c7f4cdff6a25c",
                "srcKUID": "fd3eb3ca751e4798b59a12af8de4fd04",
                "wType": "FlexContainer"
            }
        },
        "flxSearch": {
            "__events__": {},
            "__info__": {
                "kuid": "f118abb4ab7d45e19e26a9c77ac7ad9c",
                "srcKUID": "f46eab5e257a4a5faca8d9c8b16f58bb",
                "wType": "FlexContainer"
            },
            "isVisible": false
        },
        "imgBack": {
            "__events__": {},
            "__info__": {
                "kuid": "d1b3ebac119e42e4a2174dc7a2e869ae",
                "srcKUID": "a54167a680ef4852826dcbc71ac31f89",
                "wType": "Image"
            }
        },
        "imgSearch": {
            "__events__": {},
            "__info__": {
                "kuid": "c5e1463c7f7742efa3b727fdfe7fac26",
                "srcKUID": "d5b6a4c443884b6e920a9e69bfa3cf50",
                "wType": "Image"
            }
        },
        "lblLocateUs": {
            "__events__": {},
            "__info__": {
                "kuid": "c4fb9db5b9554878945d548e1ff249e9",
                "srcKUID": "c6589a12cf8e43e685fa0a5b4a9223f6",
                "wType": "Label"
            },
            "text": "Confirm Transfer",
            "i18n_text": "kony.mb.checkDeposit.confirmTransfer"
        }
    },
    "id": "customHeader",
    "info": null,
    "iscustomlayout": false,
    "isdatareferenced": false,
    "isvisible": true,
    "kuid": "e46b5f2e50354245a4a6f5ab32b56e46",
    "layouttype": 2,
    "masterType": 0,
    "name": "kony.ui.UserWidgetInstance",
    "parent": "flxHeader",
    "pf": "frmCardLessConfWithdrawQR",
    "retaincontentalignment": false,
    "retainflexpositionproperties": false,
    "snaptogrid": true,
    "sourceUserWidget": "cf270a797f14497bb1bba45b251f1a06",
    "wType": "UserWidgetInstance"
}