{
    "@class": "com.kony.gen.viz.model.component.KVizUserWidget",
    "DNDConfig": null,
    "__parentReadjusting__": false,
    "_children_": [],
    "_height_": {
        "type": "string",
        "value": "80dp"
    },
    "_left_": {
        "type": "string",
        "value": "0dp"
    },
    "_margin_": [
        0,
        0,
        0,
        0
    ],
    "_orientation_": 1,
    "_padding_": [
        0,
        0,
        0,
        0
    ],
    "_percent_": true,
    "_render_": true,
    "_skin_": "sb4decdc485c46fa889333f8f05dc888",
    "_top_": {
        "type": "string",
        "value": "0dp"
    },
    "_width_": {
        "type": "string",
        "value": "100%"
    },
    "areflexpropsreferenced": false,
    "canUpdateUI": true,
    "clipbounds": false,
    "containerweight": 0,
    "dataDiffs": {
        "customFooter": {
            "__events__": {},
            "__info__": {
                "isRoot": true,
                "kuid": "c0354f59b850491b84d66a97a18cf26d",
                "srcKUID": "j2769f86ac784eb5b787844f68df6529",
                "wType": "FlexContainer"
            }
        },
        "flxAccSelect": {
            "__events__": {},
            "__info__": {
                "kuid": "h8b6a029d9d2446dbaa2cee352e7bde5",
                "srcKUID": "aa0f7dd3579f40f8b3761978e1f2437e",
                "wType": "FlexContainer"
            }
        },
        "flxAccounts": {
            "__events__": {},
            "__info__": {
                "kuid": "j5311dbf761f4eb0b00f1e92fa43a294",
                "srcKUID": "a23db3ca5ab7413f83ea2578df1e30bc",
                "wType": "FlexContainer"
            }
        },
        "flxBillPay": {
            "__events__": {},
            "__info__": {
                "kuid": "de98c9a810e64bd88440a4fcae2065d6",
                "srcKUID": "ce792fdbe51349efb4a3f4947df64370",
                "wType": "FlexContainer"
            }
        },
        "flxBillPaySelect": {
            "__events__": {},
            "__info__": {
                "kuid": "h7118a0178dc420090e3d386167625ed",
                "srcKUID": "j2758c84af8242c88ddef570ebebb617",
                "wType": "FlexContainer"
            }
        },
        "flxContainer": {
            "__events__": {},
            "__info__": {
                "kuid": "d8b3c2d1aaa3448391187bb4c7bc96be",
                "srcKUID": "j914e21110dc4591b1b8a54fb81dd58b",
                "wType": "FlexContainer"
            }
        },
        "flxDeposits": {
            "__events__": {},
            "__info__": {
                "kuid": "f5fd01e85205422ab3284388784cf12e",
                "srcKUID": "h9152d28a3e343de99ca644e9db24232",
                "wType": "FlexContainer"
            }
        },
        "flxDepositsSelect": {
            "__events__": {},
            "__info__": {
                "kuid": "a593b06bb9554fdca21b421c27ce3b13",
                "srcKUID": "bedc1735323f42728a1fd81a8930b518",
                "wType": "FlexContainer"
            }
        },
        "flxMenu": {
            "__events__": {},
            "__info__": {
                "kuid": "eeac9d0083bc417f820f17db16ab4e50",
                "srcKUID": "abf7146be07a4a97a180b8c8a3b87a5e",
                "wType": "FlexContainer"
            }
        },
        "flxMenuSelect": {
            "__events__": {},
            "__info__": {
                "kuid": "h2bd138c0b7243038e71d43fc3a2b9ea",
                "srcKUID": "g5309e636f7f46f3bb7a5d8a698ada18",
                "wType": "FlexContainer"
            }
        },
        "flxMessage": {
            "__events__": {},
            "__info__": {
                "kuid": "adaddd62ad9a40338cc7e6130ad63657",
                "srcKUID": "jcba02c6a2a94152bb7836117f4df6b9",
                "wType": "FlexContainer"
            }
        },
        "flxMessageSelect": {
            "__events__": {},
            "__info__": {
                "kuid": "a60160170145497cb0f9e98210e8812b",
                "srcKUID": "aa55db25f18b4e058c5e1f4cc3f49f2f",
                "wType": "FlexContainer"
            }
        },
        "flxTransfer": {
            "__events__": {},
            "__info__": {
                "kuid": "f740965d512446dfa8475b8a3132c51f",
                "srcKUID": "a0d2968e58e14d829898832a361bbdb2",
                "wType": "FlexContainer"
            }
        },
        "flxTransferSelect": {
            "__events__": {},
            "__info__": {
                "kuid": "e680297cc92446c8b9697f5651f37f07",
                "srcKUID": "d376b4b5e07543c1af9faa0b194236a0",
                "wType": "FlexContainer"
            }
        },
        "flxTypeOneShadow": {
            "__events__": {},
            "__info__": {
                "kuid": "f353b4fa3f0a4fb3b9577309d8d9d5dc",
                "srcKUID": "g18525a8011345698b239ca8719d3166",
                "wType": "FlexContainer"
            }
        },
        "imgAccounts": {
            "__events__": {},
            "__info__": {
                "kuid": "c51d1d36791d4b998e16190a911e4677",
                "srcKUID": "cd8ded06a99b4ffe8858f8b54fa70f83",
                "wType": "Image"
            }
        },
        "imgBillPay": {
            "__events__": {},
            "__info__": {
                "kuid": "da04973368f3447386ad239ff208ac77",
                "srcKUID": "b7fb43c925684289b54c52defdc45620",
                "wType": "Image"
            }
        },
        "imgDeposits": {
            "__events__": {},
            "__info__": {
                "kuid": "hf6483c2f69a47f19a08d07f5e9fff93",
                "srcKUID": "cf11a27a53cc46bb933ce76bcf7c81b5",
                "wType": "Image"
            }
        },
        "imgMenu": {
            "__events__": {},
            "__info__": {
                "kuid": "e5d4e900e733456986ea55b1abe28140",
                "srcKUID": "bf31d41560da4a3392caa737c00f0fa5",
                "wType": "Image"
            }
        },
        "imgMessage": {
            "__events__": {},
            "__info__": {
                "kuid": "cb2f933761e7457ab2271c3016f305a4",
                "srcKUID": "g292625c1eca45b0ac9eba6607089c60",
                "wType": "Image"
            }
        },
        "imgTransfer": {
            "__events__": {},
            "__info__": {
                "kuid": "d7a8d45ce2ba4e4480b6dc9d6006f0d0",
                "srcKUID": "db0c718faf3f440f8e2b64923bb3bd49",
                "wType": "Image"
            }
        },
        "lblAccounts": {
            "__events__": {},
            "__info__": {
                "kuid": "h32bbd2ad53446cebc6adb2418445a61",
                "srcKUID": "e0a9c954b4a94eb89867a641d1d9df03",
                "wType": "Label"
            }
        },
        "lblBillPay": {
            "__events__": {},
            "__info__": {
                "kuid": "b7642b8e5f2d4d3689e12e9898ea780f",
                "srcKUID": "b44b3c0d9e394b9fb1b724b741d266f7",
                "wType": "Label"
            }
        },
        "lblDeposits": {
            "__events__": {},
            "__info__": {
                "kuid": "ea8eca3304d541e7811ac02a67435330",
                "srcKUID": "ce2a316eac8643629120a1dbd2ea1c9e",
                "wType": "Label"
            }
        },
        "lblMenu": {
            "__events__": {},
            "__info__": {
                "kuid": "h3539d60ea144e978a91f897d828b489",
                "srcKUID": "afc2c9edbe184367930355a6dce0b0d2",
                "wType": "Label"
            }
        },
        "lblMessage": {
            "__events__": {},
            "__info__": {
                "kuid": "aa8dd3da58f84fba8b1e6e6ed30cb040",
                "srcKUID": "d65b6b2e57b242ce8d8601f26aaae221",
                "wType": "Label"
            }
        },
        "lblTransfer": {
            "__events__": {},
            "__info__": {
                "kuid": "c6fe7510b3b04639bd06c35726422a0f",
                "srcKUID": "g689e99965344298a9d10d41665d60a3",
                "wType": "Label"
            }
        }
    },
    "id": "customFooter",
    "info": null,
    "iscustomlayout": false,
    "isdatareferenced": false,
    "isvisible": true,
    "kuid": "c0354f59b850491b84d66a97a18cf26d",
    "layouttype": 2,
    "masterType": 0,
    "name": "kony.ui.UserWidgetInstance",
    "parent": "flxFooter",
    "pf": "frmTransfers",
    "retaincontentalignment": false,
    "retainflexpositionproperties": false,
    "snaptogrid": true,
    "sourceUserWidget": "j2769f86ac784eb5b787844f68df6529",
    "wType": "UserWidgetInstance"
}