{
    "AS_Form_a61f5305a38044e4b521eedada9f4f32": {
        "id": "AS_Form_a61f5305a38044e4b521eedada9f4f32",
        "type": "ACTION_SEQUENCE",
        "params": [{
            "datatype": "collection",
            "name": "eventobject"
        }],
        "contextObj": {
            "name": "frmManageTransferRecipient",
            "type": "forms",
            "platform": null,
            "KUID": "d31df5820d5b44d8bfcc1bc4f52d6349"
        },
        "language": "js",
        "actions": [{
            "id": "ADD_SNIPPET_ide_preShow_i21922da49b14401afb1501226b7d07a",
            "type": "ADD_SNIPPET",
            "codeSnippet": "this.preShow();",
            "callbackType": null
        }]
    }
}