{
    "AS_Form_fb12776f37484c739844e1fe1098cb22": {
        "id": "AS_Form_fb12776f37484c739844e1fe1098cb22",
        "type": "ACTION_SEQUENCE",
        "params": [{
            "datatype": "collection",
            "name": "eventobject"
        }],
        "contextObj": {
            "name": "frmProfileEnterEmailID",
            "type": "forms",
            "platform": null,
            "KUID": "ccda13b764eb408680e6237341e1bb77"
        },
        "language": "js",
        "actions": [{
            "id": "ADD_SNIPPET_ide_preShow_d703af8eddaa468f8f13df8939c7250e",
            "type": "ADD_SNIPPET",
            "codeSnippet": "this.frmEnrollLAstNamePreShow();",
            "callbackType": null
        }]
    }
}