{
    "AS_Form_f3c8bbd1ebbb4b23be522ad474fe278d": {
        "id": "AS_Form_f3c8bbd1ebbb4b23be522ad474fe278d",
        "type": "ACTION_SEQUENCE",
        "params": [{
            "datatype": "collection",
            "name": "eventobject"
        }],
        "contextObj": {
            "name": "frmEnterBenAccNoEurope",
            "type": "forms",
            "platform": null,
            "KUID": "i7fcb0574dc84af8b7c23cefc21a3573"
        },
        "language": "js",
        "actions": [{
            "id": "ADD_SNIPPET_ide_init_c6adce471c524002ac058e4e8747b352",
            "type": "ADD_SNIPPET",
            "codeSnippet": "this.init();",
            "callbackType": null
        }]
    }
}